{"activityId": 18725762655, "activityUUID": {"uuid": "77475d7f-9ec3-478c-91db-26e57e76c6aa"}, "activityName": "Haarlem Running", "userProfileId": 131775658, "isMultiSportParent": false, "activityTypeDTO": {"typeId": 1, "typeKey": "running", "parentTypeId": 17, "isHidden": false, "restricted": false, "trimmable": true}, "eventTypeDTO": {"typeId": 9, "typeKey": "uncategorized", "sortOrder": 10}, "accessControlRuleDTO": {"typeId": 2, "typeKey": "private"}, "timeZoneUnitDTO": {"unitId": 124, "unitKey": "Europe/Paris", "factor": 0.0, "timeZone": "Europe/Paris"}, "metadataDTO": {"isOriginal": true, "deviceApplicationInstallationId": 979478, "agentApplicationInstallationId": null, "agentString": null, "fileFormat": {"formatId": 7, "formatKey": "fit"}, "associatedCourseId": null, "lastUpdateDate": "2025-04-04T06:39:02.0", "uploadedDate": "2025-04-04T06:39:01.0", "videoUrl": null, "hasPolyline": true, "hasChartData": true, "hasHrTimeInZones": true, "hasPowerTimeInZones": true, "userInfoDto": {"userProfilePk": 131775658, "displayname": "8ef73e80-94e2-48e0-b1c7-bfb035f3b844", "fullname": "Betul Ince", "profileImageUrlLarge": "https://connect.garmin.com/images/avatars/avatar_53088a31-3847-4fac-a4f2-fd17f78778ea.png", "profileImageUrlMedium": "https://connect.garmin.com/images/avatars/avatar_53088a31-3847-4fac-a4f2-fd17f78778ea_m.png", "profileImageUrlSmall": "https://connect.garmin.com/images/avatars/avatar_53088a31-3847-4fac-a4f2-fd17f78778ea_s.png", "userPro": false}, "childIds": [], "childActivityTypes": [], "sensors": null, "activityImages": [], "manufacturer": "GARMIN", "diveNumber": null, "lapCount": 5, "associatedWorkoutId": null, "isAtpActivity": null, "deviceMetaDataDTO": {"deviceId": "3500213516", "deviceTypePk": 37125, "deviceVersionPk": 979478}, "hasIntensityIntervals": false, "hasSplits": true, "eBikeMaxAssistModes": null, "eBikeBatteryUsage": null, "eBikeBatteryRemaining": null, "eBikeAssistModeInfoDTOList": null, "hasRunPowerWindData": false, "calendarEventInfo": null, "groupRideUUID": null, "hasHeatMap": false, "personalRecord": false, "trimmed": false, "elevationCorrected": false, "autoCalcCalories": false, "favorite": false, "manualActivity": false, "runPowerWindDataEnabled": true, "gcj02": false}, "summaryDTO": {"startTimeLocal": "2025-04-04T07:43:47.0", "startTimeGMT": "2025-04-04T05:43:47.0", "startLatitude": 52.378424406051636, "startLongitude": 4.62750842794776, "distance": 6476.64, "duration": 2911.841, "movingDuration": 2700.0, "elapsedDuration": 2914.304, "elevationGain": 5.0, "elevationLoss": 6.0, "maxElevation": 0.0, "minElevation": -3.2, "averageSpeed": 2.2239999771118164, "averageMovingSpeed": 2.39875560619213, "maxSpeed": 4.320000171661377, "calories": 479.0, "bmrCalories": 58.0, "averageHR": 161.0, "maxHR": 184.0, "minHR": 101.0, "averageRunCadence": 142.15625, "maxRunCadence": 228.0, "averagePower": 190.0, "maxPower": 405.0, "minPower": 0.0, "normalizedPower": 223.0, "totalWork": 132.2189392890726, "groundContactTime": 260.29998779296875, "strideLength": 90.97000122070312, "verticalOscillation": 7.800000000000001, "trainingEffect": 4.099999904632568, "anaerobicTrainingEffect": 2.200000047683716, "aerobicTrainingEffectMessage": "HIGHLY_IMPROVING_VO2_MAX_16", "anaerobicTrainingEffectMessage": "MAINTAINING_ANAEROBIC_BASE_1", "verticalRatio": 8.739999771118164, "endLatitude": 52.376825558021665, "endLongitude": 4.638778734952211, "maxVerticalSpeed": 0.39999997615814215, "waterEstimated": 499.0, "trainingEffectLabel": "VO2MAX", "minActivityLapDuration": 110.731, "directWorkoutFeel": 25, "directWorkoutRpe": 40, "moderateIntensityMinutes": 6, "vigorousIntensityMinutes": 42, "steps": 7170, "recoveryHeartRate": 0, "differenceBodyBattery": -17}, "locationName": "Haarlem", "splitSummaries": [{"distance": 5657.75, "duration": 2210.906, "movingDuration": 2167.0, "elevationGain": 5.0, "elevationLoss": 5.0, "averageSpeed": 2.559000015258789, "averageMovingSpeed": 2.6096155109075116, "maxSpeed": 4.320000171661377, "calories": 380.0, "bmrCalories": 44.0, "averageHR": 164.0, "maxHR": 184.0, "averageRunCadence": 163.828125, "maxRunCadence": 228.0, "averagePower": 232.0, "maxPower": 405.0, "normalizedPower": 239.0, "groundContactTime": 258.70001220703125, "strideLength": 94.07999877929689, "verticalOscillation": 8.200000000000001, "verticalRatio": 8.819999694824219, "totalExerciseReps": 0, "avgVerticalSpeed": 0.0, "splitType": "RWD_RUN", "noOfSplits": 17, "maxElevationGain": 2.0, "averageElevationGain": 0.0, "maxDistance": 752, "maxDistanceWithPrecision": 752.54}, {"distance": 93.97, "duration": 167.003, "movingDuration": 0.0, "elevationGain": 0.0, "elevationLoss": 0.0, "averageSpeed": 0.5630000233650208, "maxSpeed": 0.0, "calories": 28.0, "bmrCalories": 3.0, "averageHR": 159.0, "maxHR": 180.0, "averageRunCadence": 29.5, "maxRunCadence": 150.0, "averagePower": 0.0, "maxPower": 0.0, "normalizedPower": 133.0, "strideLength": 7.181476120353021, "totalExerciseReps": 0, "avgVerticalSpeed": 0.0, "splitType": "RWD_STAND", "noOfSplits": 11, "maxElevationGain": 0.0, "averageElevationGain": 0.0, "maxDistance": 22, "maxDistanceWithPrecision": 22.37}, {"distance": 724.92, "duration": 534.922, "movingDuration": 511.0, "elevationGain": 0.0, "elevationLoss": 1.0, "averageSpeed": 1.3550000190734863, "averageMovingSpeed": 1.3886672207344233, "maxSpeed": 2.118000030517578, "calories": 71.0, "bmrCalories": 11.0, "averageHR": 151.0, "maxHR": 180.0, "averageRunCadence": 99.015625, "maxRunCadence": 228.0, "averagePower": 77.0, "maxPower": 179.0, "normalizedPower": 109.0, "groundContactTime": 442.1000061035156, "strideLength": 71.80999755859375, "verticalOscillation": 5.8599998474121096, "verticalRatio": 8.260000228881836, "totalExerciseReps": 0, "avgVerticalSpeed": 0.0, "splitType": "RWD_WALK", "noOfSplits": 16, "maxElevationGain": 0.0, "averageElevationGain": 0.0, "maxDistance": 177, "maxDistanceWithPrecision": 177.71}]}