{"activityId": 18725762655, "activityName": "Haarlem Running", "startTimeLocal": "2025-04-04 07:43:47", "startTimeGMT": "2025-04-04 05:43:47", "activityType": {"typeId": 1, "typeKey": "running", "parentTypeId": 17, "isHidden": false, "restricted": false, "trimmable": true}, "eventType": {"typeId": 9, "typeKey": "uncategorized", "sortOrder": 10}, "distance": 6476.64013671875, "duration": 2911.841064453125, "elapsedDuration": 2914.303955078125, "movingDuration": 2700.0, "elevationGain": 5.0, "elevationLoss": 6.0, "averageSpeed": 2.2239999771118164, "maxSpeed": 4.320000171661377, "startLatitude": 52.378424406051636, "startLongitude": 4.62750842794776, "hasPolyline": true, "hasImages": false, "ownerId": 131775658, "ownerDisplayName": "8ef73e80-94e2-48e0-b1c7-bfb035f3b844", "ownerFullName": "Betul Ince", "ownerProfileImageUrlSmall": "https://connect.garmin.com/images/avatars/avatar_53088a31-3847-4fac-a4f2-fd17f78778ea_s.png", "ownerProfileImageUrlMedium": "https://connect.garmin.com/images/avatars/avatar_53088a31-3847-4fac-a4f2-fd17f78778ea_m.png", "ownerProfileImageUrlLarge": "https://connect.garmin.com/images/avatars/avatar_53088a31-3847-4fac-a4f2-fd17f78778ea.png", "calories": 479.0, "bmrCalories": 58.0, "averageHR": 161.0, "maxHR": 184.0, "averageRunningCadenceInStepsPerMinute": 142.15625, "maxRunningCadenceInStepsPerMinute": 228.0, "steps": 7170, "userRoles": ["SCOPE_GOLF_API_READ", "SCOPE_ATP_READ", "SCOPE_DIVE_API_WRITE", "SCOPE_COMMUNITY_COURSE_ADMIN_READ", "SCOPE_DIVE_API_READ", "SCOPE_DI_OAUTH_2_CLIENT_READ", "SCOPE_CONNECT_WRITE", "SCOPE_COMMUNITY_COURSE_WRITE", "SCOPE_MESSAGE_GENERATION_READ", "SCOPE_DI_OAUTH_2_CLIENT_REVOCATION_ADMIN", "SCOPE_CONNECT_WEB_TEMPLATE_RENDER", "SCOPE_OMT_SUBSCRIPTION_ADMIN_READ", "SCOPE_CONNECT_NON_SOCIAL_SHARED_READ", "SCOPE_CONNECT_READ", "SCOPE_DI_OAUTH_2_PRERELEASE_PERMISSIONS_ADMIN_WRITE", "SCOPE_DI_OAUTH_2_TOKEN_ADMIN", "ROLE_CONNECTUSER", "ROLE_FITNESS_USER", "ROLE_WELLNESS_USER"], "privacy": {"typeId": 2, "typeKey": "private"}, "userPro": false, "hasVideo": false, "timeZoneId": 124, "beginTimestamp": 1743745427000, "sportTypeId": 1, "avgPower": 190.0, "maxPower": 405.0, "aerobicTrainingEffect": 4.099999904632568, "anaerobicTrainingEffect": 2.200000047683716, "normPower": 223.0, "avgVerticalOscillation": 7.800000000000001, "avgGroundContactTime": 260.29998779296875, "avgStrideLength": 90.97000122070312, "vO2MaxValue": 45.0, "avgVerticalRatio": 8.739999771118164, "deviceId": 3500213516, "minElevation": -3.200000047683716, "maxElevation": 0.0, "maxDoubleCadence": 228.0, "summarizedDiveInfo": {"summarizedDiveGases": []}, "maxVerticalSpeed": 0.39999997615814215, "manufacturer": "GARMIN", "locationName": "Haarlem", "lapCount": 5, "endLatitude": 52.376825558021665, "endLongitude": 4.638778734952211, "waterEstimated": 499.0, "trainingEffectLabel": "VO2MAX", "minActivityLapDuration": 110.73100280761719, "aerobicTrainingEffectMessage": "HIGHLY_IMPROVING_VO2_MAX_16", "anaerobicTrainingEffectMessage": "MAINTAINING_ANAEROBIC_BASE_1", "splitSummaries": [{"noOfSplits": 17, "totalAscent": 5.0, "duration": 2210.906005859375, "splitType": "RWD_RUN", "numClimbSends": 0, "maxElevationGain": 2.0, "averageElevationGain": 0.0, "maxDistance": 752, "distance": 5657.75, "averageSpeed": 2.559000015258789, "maxSpeed": 4.320000171661377, "numFalls": 0, "elevationLoss": 5.0}, {"noOfSplits": 11, "totalAscent": 0.0, "duration": 167.0030059814453, "splitType": "RWD_STAND", "numClimbSends": 0, "maxElevationGain": 0.0, "averageElevationGain": 0.0, "maxDistance": 22, "distance": 93.97000122070312, "averageSpeed": 0.5630000233650208, "maxSpeed": 0.0, "numFalls": 0, "elevationLoss": 0.0}, {"noOfSplits": 16, "totalAscent": 0.0, "duration": 534.9219970703125, "splitType": "RWD_WALK", "numClimbSends": 0, "maxElevationGain": 0.0, "averageElevationGain": 0.0, "maxDistance": 177, "distance": 724.9199829101562, "averageSpeed": 1.3550000190734863, "maxSpeed": 2.118000030517578, "numFalls": 0, "elevationLoss": 1.0}], "hasSplits": true, "moderateIntensityMinutes": 6, "vigorousIntensityMinutes": 42, "differenceBodyBattery": -17, "hasHeatMap": false, "fastestSplit_1000": 381.9429931640625, "fastestSplit_1609": 629.0479736328125, "fastestSplit_5000": 2250.40087890625, "hrTimeInZone_1": 11.082, "hrTimeInZone_2": 188.0, "hrTimeInZone_3": 732.928, "hrTimeInZone_4": 1350.863, "hrTimeInZone_5": 628.836, "powerTimeInZone_1": 1066.982, "powerTimeInZone_2": 748.851, "powerTimeInZone_3": 135.997, "powerTimeInZone_4": 21.999, "powerTimeInZone_5": 4.001, "endTimeGMT": "2025-04-04 06:32:21", "qualifyingDive": false, "purposeful": false, "manualActivity": false, "pr": false, "parent": false, "favorite": false, "decoDive": false, "autoCalcCalories": false, "elevationCorrected": false, "atpActivity": false}