{"userProfileId": 131775658, "totalKilocalories": 2360.0, "activeKilocalories": 649.0, "bmrKilocalories": 1711.0, "wellnessKilocalories": 2360.0, "burnedKilocalories": null, "consumedKilocalories": null, "remainingKilocalories": null, "totalSteps": 14394, "netCalorieGoal": null, "totalDistanceMeters": 11868, "wellnessDistanceMeters": 11868, "wellnessActiveKilocalories": 649.0, "netRemainingKilocalories": 649.0, "userDailySummaryId": 131775658, "calendarDate": "2025-04-04", "rule": {"typeId": 2, "typeKey": "private"}, "uuid": "ce95966cee7c49e3aa2f0691ba21a217", "dailyStepGoal": 8280, "wellnessStartTimeGmt": "2025-04-03T22:00:00.0", "wellnessStartTimeLocal": "2025-04-04T00:00:00.0", "wellnessEndTimeGmt": "2025-04-04T22:00:00.0", "wellnessEndTimeLocal": "2025-04-05T00:00:00.0", "durationInMilliseconds": 86400000, "wellnessDescription": null, "highlyActiveSeconds": 5779, "activeSeconds": 2031, "sedentarySeconds": 78590, "sleepingSeconds": 0, "includesWellnessData": true, "includesActivityData": true, "includesCalorieConsumedData": false, "privacyProtected": false, "moderateIntensityMinutes": 8, "vigorousIntensityMinutes": 45, "floorsAscendedInMeters": 12.192, "floorsDescendedInMeters": 17.705, "floorsAscended": 4.0, "floorsDescended": 5.80873, "intensityMinutesGoal": 150, "userFloorsAscendedGoal": 10, "minHeartRate": 47, "maxHeartRate": 180, "restingHeartRate": 53, "lastSevenDaysAvgRestingHeartRate": 55, "source": "GARMIN", "averageStressLevel": 14, "maxStressLevel": 85, "stressDuration": 6240, "restStressDuration": 56880, "activityStressDuration": 9900, "uncategorizedStressDuration": 6240, "totalStressDuration": 79260, "lowStressDuration": 5400, "mediumStressDuration": 720, "highStressDuration": 120, "stressPercentage": 7.87, "restStressPercentage": 71.76, "activityStressPercentage": 12.49, "uncategorizedStressPercentage": 7.87, "lowStressPercentage": 6.81, "mediumStressPercentage": 0.91, "highStressPercentage": 0.15, "stressQualifier": "CALM_AWAKE", "measurableAwakeDuration": 73020, "measurableAsleepDuration": 0, "lastSyncTimestampGMT": null, "minAvgHeartRate": 49, "maxAvgHeartRate": 179, "bodyBatteryChargedValue": 19, "bodyBatteryDrainedValue": 52, "bodyBatteryHighestValue": 100, "bodyBatteryLowestValue": 51, "bodyBatteryMostRecentValue": 51, "bodyBatteryDuringSleep": null, "bodyBatteryAtWakeTime": null, "bodyBatteryVersion": 3.0, "abnormalHeartRateAlertsCount": null, "averageSpo2": null, "lowestSpo2": null, "latestSpo2": null, "latestSpo2ReadingTimeGmt": null, "latestSpo2ReadingTimeLocal": null, "averageMonitoringEnvironmentAltitude": -20.0, "restingCaloriesFromActivity": 58.0, "bodyBatteryDynamicFeedbackEvent": {"eventTimestampGmt": "2025-04-04T19:35:00", "bodyBatteryLevel": "HIGH", "feedbackShortType": "SLEEP_PREPARATION_RECOVERING_AND_INTENSIVE_EXERCISE", "feedbackLongType": "SLEEP_PREPARATION_RECOVERING_AND_INTENSIVE_EXERCISE"}, "bodyBatteryActivityEventList": [{"eventType": "ACTIVITY", "eventStartTimeGmt": "2025-04-04T05:43:47", "timezoneOffset": 7200000, "durationInMilliseconds": 2880000, "bodyBatteryImpact": -18, "feedbackType": "EXERCISE_TRAINING_EFFECT_4_GOOD_TIMING", "shortFeedback": "HIGHLY_IMPROVING_VO2MAX", "deviceId": 3500213516, "activityName": "Haarlem Running", "activityType": "running", "activityId": 18725762655, "eventUpdateTimeGmt": "2025-04-04T06:33:05"}, {"eventType": "RECOVERY", "eventStartTimeGmt": "2025-04-04T08:17:10", "timezoneOffset": 7200000, "durationInMilliseconds": 2640000, "bodyBatteryImpact": 0, "feedbackType": "RECOVERY_BODY_BATTERY_NOT_INCREASE", "shortFeedback": "RESTFUL_PERIOD", "deviceId": 3500213516, "activityName": null, "activityType": null, "activityId": null, "eventUpdateTimeGmt": "2025-04-04T09:13:16"}, {"eventType": "RECOVERY", "eventStartTimeGmt": "2025-04-04T09:13:05", "timezoneOffset": 7200000, "durationInMilliseconds": 19140000, "bodyBatteryImpact": 1, "feedbackType": "RECOVERY_LONG_BODY_BATTERY_INCREASE", "shortFeedback": "LONG_RESTFUL_PERIOD", "deviceId": 3500213516, "activityName": null, "activityType": null, "activityId": null, "eventUpdateTimeGmt": "2025-04-04T14:36:35"}, {"eventType": "RECOVERY", "eventStartTimeGmt": "2025-04-04T18:29:30", "timezoneOffset": 7200000, "durationInMilliseconds": 2220000, "bodyBatteryImpact": -1, "feedbackType": "RECOVERY_BODY_BATTERY_NOT_INCREASE", "shortFeedback": "RESTFUL_PERIOD", "deviceId": 3500213516, "activityName": null, "activityType": null, "activityId": null, "eventUpdateTimeGmt": "2025-04-04T19:11:12"}], "avgWakingRespirationValue": 14.0, "highestRespirationValue": 25.0, "lowestRespirationValue": 8.0, "latestRespirationValue": 13.0, "latestRespirationTimeGMT": "2025-04-04T21:15:00.0", "respirationAlgorithmVersion": 200}