{"userProfileId": 131775658, "totalKilocalories": 2135.0, "activeKilocalories": 424.0, "bmrKilocalories": 1711.0, "wellnessKilocalories": 2135.0, "burnedKilocalories": null, "consumedKilocalories": null, "remainingKilocalories": null, "totalSteps": 18008, "netCalorieGoal": null, "totalDistanceMeters": 13463, "wellnessDistanceMeters": 13463, "wellnessActiveKilocalories": 424.0, "netRemainingKilocalories": 424.0, "userDailySummaryId": 131775658, "calendarDate": "2025-05-17", "rule": {"typeId": 2, "typeKey": "private"}, "uuid": "0cf04ca78cd341b4bc267b66ff726744", "dailyStepGoal": 9770, "wellnessStartTimeGmt": "2025-05-16T22:00:00.0", "wellnessStartTimeLocal": "2025-05-17T00:00:00.0", "wellnessEndTimeGmt": "2025-05-17T22:00:00.0", "wellnessEndTimeLocal": "2025-05-18T00:00:00.0", "durationInMilliseconds": 86400000, "wellnessDescription": null, "highlyActiveSeconds": 2509, "activeSeconds": 6721, "sedentarySeconds": 77170, "sleepingSeconds": 0, "includesWellnessData": true, "includesActivityData": false, "includesCalorieConsumedData": false, "privacyProtected": false, "moderateIntensityMinutes": 12, "vigorousIntensityMinutes": 0, "floorsAscendedInMeters": 8.206, "floorsDescendedInMeters": 6.388, "floorsAscended": 2.69226, "floorsDescended": 2.0958, "intensityMinutesGoal": 150, "userFloorsAscendedGoal": 10, "minHeartRate": 52, "maxHeartRate": 117, "restingHeartRate": 60, "lastSevenDaysAvgRestingHeartRate": 62, "source": "GARMIN", "averageStressLevel": 23, "maxStressLevel": 70, "stressDuration": 4200, "restStressDuration": 10260, "activityStressDuration": 11700, "uncategorizedStressDuration": 55800, "totalStressDuration": 81960, "lowStressDuration": 3420, "mediumStressDuration": 780, "highStressDuration": null, "stressPercentage": 5.12, "restStressPercentage": 12.52, "activityStressPercentage": 14.28, "uncategorizedStressPercentage": 68.08, "lowStressPercentage": 4.17, "mediumStressPercentage": 0.95, "highStressPercentage": 0.0, "stressQualifier": "UNKNOWN", "measurableAwakeDuration": 26160, "measurableAsleepDuration": 0, "lastSyncTimestampGMT": null, "minAvgHeartRate": 53, "maxAvgHeartRate": 115, "bodyBatteryChargedValue": 0, "bodyBatteryDrainedValue": 50, "bodyBatteryHighestValue": 78, "bodyBatteryLowestValue": 25, "bodyBatteryMostRecentValue": 29, "bodyBatteryDuringSleep": null, "bodyBatteryAtWakeTime": null, "bodyBatteryVersion": 3.0, "abnormalHeartRateAlertsCount": null, "averageSpo2": null, "lowestSpo2": null, "latestSpo2": null, "latestSpo2ReadingTimeGmt": null, "latestSpo2ReadingTimeLocal": null, "averageMonitoringEnvironmentAltitude": 23.0, "restingCaloriesFromActivity": null, "bodyBatteryDynamicFeedbackEvent": {"eventTimestampGmt": "2025-05-17T21:48:56", "bodyBatteryLevel": "MODERATE", "feedbackShortType": "NO_DATA", "feedbackLongType": "NO_DATA"}, "endOfDayBodyBatteryDynamicFeedbackEvent": {"eventTimestampGmt": "2025-05-16T22:52:34", "bodyBatteryLevel": "HIGH", "feedbackShortType": "SLEEP_TIME_PASSED_NOT_STRESS_DATA_AND_INACTIVE", "feedbackLongType": "SLEEP_TIME_PASSED_NOT_STRESS_DATA_AND_INACTIVE"}, "bodyBatteryActivityEventList": [{"eventType": "RECOVERY", "eventStartTimeGmt": "2025-05-17T06:23:22", "timezoneOffset": 7200000, "durationInMilliseconds": 7260000, "bodyBatteryImpact": -2, "feedbackType": "RECOVERY_LONG_BODY_BATTERY_NOT_INCREASE", "shortFeedback": "LONG_RESTFUL_PERIOD", "deviceId": 3500213516, "activityName": null, "activityType": null, "activityId": null, "eventUpdateTimeGmt": "2025-05-17T08:28:47"}], "avgWakingRespirationValue": 15.0, "highestRespirationValue": 20.0, "lowestRespirationValue": 7.0, "latestRespirationValue": 16.0, "latestRespirationTimeGMT": "2025-05-17T17:53:00.0", "respirationAlgorithmVersion": 200}